<?xml version="1.0" encoding="UTF-8"?>
<page xmlns="http://jboss.org/schema/seam/pages"
      xmlns:xsi="http://www.w3.org/2001/XMLSchema-instance"
      xsi:schemaLocation="http://jboss.org/schema/seam/pages http://jboss.org/schema/seam/pages-2.3.xsd">

   <param name="firstResult" value="#{tipList.firstResult}"/>
   <param name="sort" value="#{tipList.orderColumn}"/>
   <param name="dir" value="#{tipList.orderDirection}"/>
   <param name="logic" value="#{tipList.restrictionLogicOperator}"/>

   <param name="from"/>
   <param name="contenido" value="#{tipList.tip.contenido}"/>
   <param name="usuarioAlta" value="#{tipList.tip.usuarioAlta}"/>
   <param name="usuarioModificacion" value="#{tipList.tip.usuarioModificacion}"/>
   <param name="estadoRegistro" value="#{tipList.tip.estadoRegistro}"/>

</page>
